rest_framework_filters/__init__.py
rest_framework_filters/backends.py
rest_framework_filters/filters.py
rest_framework_filters/filterset.py
rest_framework_filters/templates/rest_framework_filters/form.html
rest_framework_filters/templatetags/__init__.py
rest_framework_filters/templatetags/rest_framework_filters.py
djangorestframework_filters_mini-2023.0.0.dist-info/LICENSE
djangorestframework_filters_mini-2023.0.0.dist-info/METADATA
djangorestframework_filters_mini-2023.0.0.dist-info/WHEEL
djangorestframework_filters_mini-2023.0.0.dist-info/top_level.txt
djangorestframework_filters_mini-2023.0.0.dist-info/RECORD
