Metadata-Version: 2.1
Name: djangorestframework-filters-mini
Version: 2023.0.0
Summary: Better filtering for Django REST Framework
Home-page: https://github.com/obsrvbl-oss/django-rest-framework-filters-mini
Author: mrg29
Author-email: 40182894+mrg29@users.noreply.github.com
License: MIT
Requires-Python: >=3.9
License-File: LICENSE
Requires-Dist: djangorestframework
Requires-Dist: django-filter >=2.0
Provides-Extra: dev
Requires-Dist: black ; extra == 'dev'
Requires-Dist: coverage ; extra == 'dev'
Requires-Dist: pyflakes ; extra == 'dev'
